[1,["09W47CvINIK5YUHelmY5Js@6c48a","28OKcp1k1BT4Yi78tFc1Vt@6c48a","35ep2j9VhLUKsIlCwVglA0@6c48a","40Py2Mq5FFZLKntJnnVcJT@6c48a","51jfLS5XBETrv0Cy+w/aQr@6c48a","76TSXO+GNCV4RCFD0tMcyb@6c48a","99x9deUEhED41nrMeqk+0p@6c48a","9fCvhyG5BBmpje7mCp48hu@6c48a","b6nkea5JNMmp5BxJD1T83O@6c48a","bfgozQkOdApLUuWqe7mWqv@6c48a","ddnpC+fM1B3KUd3MFNc70G@6c48a"],["_textureSource"],["cc.SpriteFrame"],0,[[[{"name":"1934.0","rect":{"x":0,"y":0,"width":22,"height":22},"offset":{"x":0,"y":0},"originalSize":{"width":22,"height":22},"rotated":false,"capInsets":[0,0,0,0],"vertices":{"rawPosition":[-11,-11,0,11,-11,0,-11,11,0,11,11,0],"indexes":[0,1,2,2,1,3],"uv":[0,22,22,22,0,0,22,0],"nuv":[0,0,1,0,0,1,1,1],"minPos":{"x":-11,"y":-11,"z":0},"maxPos":{"x":11,"y":11,"z":0}},"packable":true,"pixelsToUnit":100,"pivot":{"x":0.5,"y":0.5},"meshType":0}],[0],0,[0],[0],[0]],[[{"name":"1932.0","rect":{"x":0,"y":0,"width":22,"height":21},"offset":{"x":0,"y":0},"originalSize":{"width":22,"height":21},"rotated":false,"capInsets":[0,0,0,0],"vertices":{"rawPosition":[-11,-10.5,0,11,-10.5,0,-11,10.5,0,11,10.5,0],"indexes":[0,1,2,2,1,3],"uv":[0,21,22,21,0,0,22,0],"nuv":[0,0,1,0,0,1,1,1],"minPos":{"x":-11,"y":-10.5,"z":0},"maxPos":{"x":11,"y":10.5,"z":0}},"packable":true,"pixelsToUnit":100,"pivot":{"x":0.5,"y":0.5},"meshType":0}],[0],0,[0],[0],[1]],[[{"name":"1929.0","rect":{"x":0,"y":0,"width":22,"height":20},"offset":{"x":0,"y":0},"originalSize":{"width":22,"height":20},"rotated":false,"capInsets":[0,0,0,0],"vertices":{"rawPosition":[-11,-10,0,11,-10,0,-11,10,0,11,10,0],"indexes":[0,1,2,2,1,3],"uv":[0,20,22,20,0,0,22,0],"nuv":[0,0,1,0,0,1,1,1],"minPos":{"x":-11,"y":-10,"z":0},"maxPos":{"x":11,"y":10,"z":0}},"packable":true,"pixelsToUnit":100,"pivot":{"x":0.5,"y":0.5},"meshType":0}],[0],0,[0],[0],[2]],[[{"name":"1937.0","rect":{"x":0,"y":0,"width":20,"height":22},"offset":{"x":0,"y":0},"originalSize":{"width":20,"height":22},"rotated":false,"capInsets":[0,0,0,0],"vertices":{"rawPosition":[-10,-11,0,10,-11,0,-10,11,0,10,11,0],"indexes":[0,1,2,2,1,3],"uv":[0,22,20,22,0,0,20,0],"nuv":[0,0,1,0,0,1,1,1],"minPos":{"x":-10,"y":-11,"z":0},"maxPos":{"x":10,"y":11,"z":0}},"packable":true,"pixelsToUnit":100,"pivot":{"x":0.5,"y":0.5},"meshType":0}],[0],0,[0],[0],[3]],[[{"name":"1935.0","rect":{"x":0,"y":0,"width":22,"height":22},"offset":{"x":0,"y":0},"originalSize":{"width":22,"height":22},"rotated":false,"capInsets":[0,0,0,0],"vertices":{"rawPosition":[-11,-11,0,11,-11,0,-11,11,0,11,11,0],"indexes":[0,1,2,2,1,3],"uv":[0,22,22,22,0,0,22,0],"nuv":[0,0,1,0,0,1,1,1],"minPos":{"x":-11,"y":-11,"z":0},"maxPos":{"x":11,"y":11,"z":0}},"packable":true,"pixelsToUnit":100,"pivot":{"x":0.5,"y":0.5},"meshType":0}],[0],0,[0],[0],[4]],[[{"name":"1931.0","rect":{"x":0,"y":0,"width":22,"height":20},"offset":{"x":0,"y":0},"originalSize":{"width":22,"height":20},"rotated":false,"capInsets":[0,0,0,0],"vertices":{"rawPosition":[-11,-10,0,11,-10,0,-11,10,0,11,10,0],"indexes":[0,1,2,2,1,3],"uv":[0,20,22,20,0,0,22,0],"nuv":[0,0,1,0,0,1,1,1],"minPos":{"x":-11,"y":-10,"z":0},"maxPos":{"x":11,"y":10,"z":0}},"packable":true,"pixelsToUnit":100,"pivot":{"x":0.5,"y":0.5},"meshType":0}],[0],0,[0],[0],[5]],[[{"name":"1936.0","rect":{"x":0,"y":0,"width":22,"height":22},"offset":{"x":0,"y":0},"originalSize":{"width":22,"height":22},"rotated":false,"capInsets":[0,0,0,0],"vertices":{"rawPosition":[-11,-11,0,11,-11,0,-11,11,0,11,11,0],"indexes":[0,1,2,2,1,3],"uv":[0,22,22,22,0,0,22,0],"nuv":[0,0,1,0,0,1,1,1],"minPos":{"x":-11,"y":-11,"z":0},"maxPos":{"x":11,"y":11,"z":0}},"packable":true,"pixelsToUnit":100,"pivot":{"x":0.5,"y":0.5},"meshType":0}],[0],0,[0],[0],[6]],[[{"name":"1933.0","rect":{"x":0,"y":0,"width":22,"height":22},"offset":{"x":0,"y":0},"originalSize":{"width":22,"height":22},"rotated":false,"capInsets":[0,0,0,0],"vertices":{"rawPosition":[-11,-11,0,11,-11,0,-11,11,0,11,11,0],"indexes":[0,1,2,2,1,3],"uv":[0,22,22,22,0,0,22,0],"nuv":[0,0,1,0,0,1,1,1],"minPos":{"x":-11,"y":-11,"z":0},"maxPos":{"x":11,"y":11,"z":0}},"packable":true,"pixelsToUnit":100,"pivot":{"x":0.5,"y":0.5},"meshType":0}],[0],0,[0],[0],[7]],[[{"name":"1928.0","rect":{"x":0,"y":0,"width":22,"height":22},"offset":{"x":0,"y":0},"originalSize":{"width":22,"height":22},"rotated":false,"capInsets":[0,0,0,0],"vertices":{"rawPosition":[-11,-11,0,11,-11,0,-11,11,0,11,11,0],"indexes":[0,1,2,2,1,3],"uv":[0,22,22,22,0,0,22,0],"nuv":[0,0,1,0,0,1,1,1],"minPos":{"x":-11,"y":-11,"z":0},"maxPos":{"x":11,"y":11,"z":0}},"packable":true,"pixelsToUnit":100,"pivot":{"x":0.5,"y":0.5},"meshType":0}],[0],0,[0],[0],[8]],[[{"name":"1930.0","rect":{"x":0,"y":0,"width":22,"height":22},"offset":{"x":0,"y":0},"originalSize":{"width":22,"height":22},"rotated":false,"capInsets":[0,0,0,0],"vertices":{"rawPosition":[-11,-11,0,11,-11,0,-11,11,0,11,11,0],"indexes":[0,1,2,2,1,3],"uv":[0,22,22,22,0,0,22,0],"nuv":[0,0,1,0,0,1,1,1],"minPos":{"x":-11,"y":-11,"z":0},"maxPos":{"x":11,"y":11,"z":0}},"packable":true,"pixelsToUnit":100,"pivot":{"x":0.5,"y":0.5},"meshType":0}],[0],0,[0],[0],[9]],[[{"name":"1927.0","rect":{"x":0,"y":0,"width":22,"height":20},"offset":{"x":0,"y":0},"originalSize":{"width":22,"height":20},"rotated":false,"capInsets":[0,0,0,0],"vertices":{"rawPosition":[-11,-10,0,11,-10,0,-11,10,0,11,10,0],"indexes":[0,1,2,2,1,3],"uv":[0,20,22,20,0,0,22,0],"nuv":[0,0,1,0,0,1,1,1],"minPos":{"x":-11,"y":-10,"z":0},"maxPos":{"x":11,"y":10,"z":0}},"packable":true,"pixelsToUnit":100,"pivot":{"x":0.5,"y":0.5},"meshType":0}],[0],0,[0],[0],[10]]]]
